selpy/__init__.py
selpy/driver.py
selpy/locator.py
selpy/store.py
selpy/variable.py
selpy/src/__init__.py
selpy/src/driver.py
selpy/src/locator.py
selpy/src/store.py
selpy/src/variable.py
selpy-0.1.1.dist-info/LICENSE
selpy-0.1.1.dist-info/LICENSE.txt
selpy-0.1.1.dist-info/METADATA
selpy-0.1.1.dist-info/WHEEL
selpy-0.1.1.dist-info/top_level.txt
selpy-0.1.1.dist-info/RECORD
